dvc_cc_connector/__init__.py
dvc_cc_connector/__main__.py
dvc_cc_connector/main.py
dvc_cc_connector/version.py
dvc_cc_connector-0.8.1.dist-info/entry_points.txt
dvc_cc_connector-0.8.1.dist-info/WHEEL
dvc_cc_connector-0.8.1.dist-info/METADATA
dvc_cc_connector-0.8.1.dist-info/RECORD
