Metadata-Version: 2.1
Name: dvc-cc-connector
Version: 0.8.1
Summary: 
License: AGPL-3.0
Author: Jonas
Author-email: jonas.annuscheit@gmail.com
Requires-Python: >=3.6,<4.0
Classifier: License :: OSI Approved :: GNU Affero General Public License v3
Classifier: Programming Language :: Python :: 3
Classifier: Programming Language :: Python :: 3.6
Classifier: Programming Language :: Python :: 3.7
Requires-Dist: argparse (>=1.4,<2.0)
Requires-Dist: pyjson (>=1.3,<2.0)
